[
  {
    "category": "Languages",
    "sub": [
      "HTML/CSS",
      "TypeScript/JavaScript",
      "Python",
      "Java",
      "C",
      "Bash"
    ]
  },
  {
    "category": "Frameworks",
    "sub": ["Node.js", "Angular", "React", "Express", "Flask", "Django"]
  },
  {
    "category": "Database",
    "sub": ["MongoDB"]
  },
  {
    "category": "Software/Tools",
    "sub": [
      "Git",
      "Figma",
      "Jira",
      "Confluence",
      "Postman",
      "Docker",
      "Photoshop",
      "Android Studio",
      "Microsoft Office"
    ]
  }
]
